{
  "entrypoints": [
    "main"
  ],
  "origins": {
    "455": [
      85,
      532,
      918,
      455
    ],
    "972": [
      972
    ],
    "17896441": [
      455,
      532,
      918
    ],
    "main": [
      303,
      532,
      179
    ],
    "runtime~main": [
      179,
      532,
      303
    ],
    "0e384e19": [
      671
    ],
    "1429a0b0": [
      204
    ],
    "1712804a": [
      729
    ],
    "1be78505": [
      532,
      972
    ],
    "1e60679b": [
      251
    ],
    "1f391b9e": [
      455,
      532,
      85
    ],
    "393be207": [
      414
    ],
    "39a3cfda": [
      321
    ],
    "3a22fe28": [
      515
    ],
    "53ccc3d4": [
      836
    ],
    "935f2afb": [
      53
    ],
    "a7838936": [
      208
    ],
    "f039c878": [
      118
    ],
    "f69a803f": [
      365
    ],
    "faaf90b2": [
      340
    ],
    "ff6a7401": [
      125
    ],
    "styles": [
      85,
      179,
      303,
      455,
      514,
      918,
      532
    ]
  },
  "assets": {
    "53": {
      "js": [
        {
          "file": "assets/js/935f2afb.366f2c1d.js",
          "hash": "def4e92bcb68c98f",
          "publicPath": "/docs/assets/js/935f2afb.366f2c1d.js"
        }
      ]
    },
    "85": {
      "js": [
        {
          "file": "assets/js/1f391b9e.e3fcbb89.js",
          "hash": "c3b249094ee8a59a",
          "publicPath": "/docs/assets/js/1f391b9e.e3fcbb89.js"
        }
      ]
    },
    "118": {
      "js": [
        {
          "file": "assets/js/f039c878.ea168215.js",
          "hash": "cb2ac5f1607afb9c",
          "publicPath": "/docs/assets/js/f039c878.ea168215.js"
        }
      ]
    },
    "125": {
      "js": [
        {
          "file": "assets/js/ff6a7401.4d82eab8.js",
          "hash": "fbfe0f18b6230605",
          "publicPath": "/docs/assets/js/ff6a7401.4d82eab8.js"
        }
      ]
    },
    "179": {
      "js": [
        {
          "file": "assets/js/main.effd74b1.js",
          "hash": "33de5f7719ea3fee",
          "publicPath": "/docs/assets/js/main.effd74b1.js"
        }
      ]
    },
    "204": {
      "js": [
        {
          "file": "assets/js/1429a0b0.b7936316.js",
          "hash": "66a515d06668a07a",
          "publicPath": "/docs/assets/js/1429a0b0.b7936316.js"
        }
      ]
    },
    "208": {
      "js": [
        {
          "file": "assets/js/a7838936.e5f44f26.js",
          "hash": "3749105d2866e2a2",
          "publicPath": "/docs/assets/js/a7838936.e5f44f26.js"
        }
      ]
    },
    "251": {
      "js": [
        {
          "file": "assets/js/1e60679b.995fa93e.js",
          "hash": "b5724566068bf62e",
          "publicPath": "/docs/assets/js/1e60679b.995fa93e.js"
        }
      ]
    },
    "303": {
      "js": [
        {
          "file": "assets/js/runtime~main.4a40ff47.js",
          "hash": "9aba85c69c974a37",
          "publicPath": "/docs/assets/js/runtime~main.4a40ff47.js"
        }
      ]
    },
    "321": {
      "js": [
        {
          "file": "assets/js/39a3cfda.1491740f.js",
          "hash": "66c793a7222cd83a",
          "publicPath": "/docs/assets/js/39a3cfda.1491740f.js"
        }
      ]
    },
    "340": {
      "js": [
        {
          "file": "assets/js/faaf90b2.864ee992.js",
          "hash": "ee50b25ace9f0009",
          "publicPath": "/docs/assets/js/faaf90b2.864ee992.js"
        }
      ]
    },
    "365": {
      "js": [
        {
          "file": "assets/js/f69a803f.866999cb.js",
          "hash": "23f5c0cfef4805a2",
          "publicPath": "/docs/assets/js/f69a803f.866999cb.js"
        }
      ]
    },
    "414": {
      "js": [
        {
          "file": "assets/js/393be207.0828d566.js",
          "hash": "4457fd405fc10eca",
          "publicPath": "/docs/assets/js/393be207.0828d566.js"
        }
      ]
    },
    "455": {
      "js": [
        {
          "file": "assets/js/455.7ef2992a.js",
          "hash": "b58c4b6e63cba0b8",
          "publicPath": "/docs/assets/js/455.7ef2992a.js"
        }
      ]
    },
    "515": {
      "js": [
        {
          "file": "assets/js/3a22fe28.0cba23db.js",
          "hash": "4afb1939c27144dd",
          "publicPath": "/docs/assets/js/3a22fe28.0cba23db.js"
        }
      ]
    },
    "532": {
      "css": [
        {
          "file": "assets/css/styles.34183494.css",
          "hash": "eac38026a1551b9a",
          "publicPath": "/docs/assets/css/styles.34183494.css"
        }
      ]
    },
    "671": {
      "js": [
        {
          "file": "assets/js/0e384e19.4872b2e0.js",
          "hash": "f703cfaa4028e638",
          "publicPath": "/docs/assets/js/0e384e19.4872b2e0.js"
        }
      ]
    },
    "729": {
      "js": [
        {
          "file": "assets/js/1712804a.aa38c952.js",
          "hash": "b8bc0dba6406cb1c",
          "publicPath": "/docs/assets/js/1712804a.aa38c952.js"
        }
      ]
    },
    "836": {
      "js": [
        {
          "file": "assets/js/53ccc3d4.92b58da1.js",
          "hash": "96e18094f5c6106c",
          "publicPath": "/docs/assets/js/53ccc3d4.92b58da1.js"
        }
      ]
    },
    "918": {
      "js": [
        {
          "file": "assets/js/17896441.fcac4501.js",
          "hash": "70c01abca381f375",
          "publicPath": "/docs/assets/js/17896441.fcac4501.js"
        }
      ]
    },
    "972": {
      "js": [
        {
          "file": "assets/js/972.b43202c5.js",
          "hash": "3e66141b01dfc49f",
          "publicPath": "/docs/assets/js/972.b43202c5.js"
        },
        {
          "file": "assets/js/1be78505.74114e91.js",
          "hash": "f2badab17e4924b6",
          "publicPath": "/docs/assets/js/1be78505.74114e91.js"
        }
      ]
    }
  }
}